LICENSE
README.md
setup.py
aiocqhttp/__init__.py
aiocqhttp/api.py
aiocqhttp/api.pyi
aiocqhttp/api_impl.py
aiocqhttp/bus.py
aiocqhttp/default.py
aiocqhttp/event.py
aiocqhttp/exceptions.py
aiocqhttp/message.py
aiocqhttp/typing.py
aiocqhttp/utils.py
aiocqhttp.egg-info/PKG-INFO
aiocqhttp.egg-info/SOURCES.txt
aiocqhttp.egg-info/dependency_links.txt
aiocqhttp.egg-info/requires.txt
aiocqhttp.egg-info/top_level.txt