Metadata-Version: 2.1
Name: aiocqhttp
Version: 1.4.4
Summary: A Python SDK with async I/O for OneBot (CQHTTP).
Home-page: https://github.com/nonebot/aiocqhttp
Author: Richard Chien
Author-email: richardchienthebest@gmail.com
Maintainer: NoneBot Team
License: MIT License
Platform: any
Classifier: Programming Language :: Python :: 3
Classifier: License :: OSI Approved :: MIT License
Classifier: Operating System :: OS Independent
Classifier: Framework :: Robot Framework
Requires-Python: >=3.7
Provides-Extra: all
